{
	"info": {
		"_postman_id": "b4f1cd6e-22a1-46e4-815d-f3c590c3c9f0",
		"name": "udacity-fsnd-udaspicelatte",
		"schema": "https://schema.getpostman.com/json/collection/v2.1.0/collection.json",
		"_exporter_id": "18696400"
	},
	"item": [
		{
			"name": "public",
			"item": [
				{
					"name": "/drinks",
					"event": [
						{
							"listen": "test",
							"script": {
								"exec": [
									"pm.test(\"Status code is 200\", function () {",
									"    pm.response.to.have.status(200);",
									"});",
									"",
									"pm.test(\"value contains drinks array\", function () {",
									"    var jsonData = pm.response.json();",
									"    pm.expect(jsonData.drinks).to.be.an('array')",
									"});"
								],
								"type": "text/javascript"
							}
						}
					],
					"request": {
						"method": "GET",
						"header": [],
						"url": {
							"raw": "{{host}}/drinks",
							"host": [
								"{{host}}"
							],
							"path": [
								"drinks"
							]
						}
					},
					"response": []
				},
				{
					"name": "/drinks-detail",
					"event": [
						{
							"listen": "test",
							"script": {
								"exec": [
									"pm.test(\"Status code is 401 since no credentials are present\", function () {",
									"    pm.response.to.have.status(401);",
									"});"
								],
								"type": "text/javascript"
							}
						}
					],
					"request": {
						"method": "GET",
						"header": [],
						"url": {
							"raw": "{{host}}/drinks-detail",
							"host": [
								"{{host}}"
							],
							"path": [
								"drinks-detail"
							]
						}
					},
					"response": []
				},
				{
					"name": "/drinks",
					"event": [
						{
							"listen": "test",
							"script": {
								"exec": [
									"pm.test(\"Status code is 401 since no credentials are present\", function () {",
									"    pm.response.to.have.status(401);",
									"});"
								],
								"type": "text/javascript"
							}
						}
					],
					"request": {
						"method": "POST",
						"header": [],
						"url": {
							"raw": "{{host}}/drinks",
							"host": [
								"{{host}}"
							],
							"path": [
								"drinks"
							]
						}
					},
					"response": []
				},
				{
					"name": "/drinks/1",
					"event": [
						{
							"listen": "test",
							"script": {
								"exec": [
									"pm.test(\"Status code is 401 since no credentials are present\", function () {",
									"    pm.response.to.have.status(401);",
									"});"
								],
								"type": "text/javascript"
							}
						}
					],
					"request": {
						"method": "PATCH",
						"header": [],
						"url": {
							"raw": "{{host}}/drinks/1",
							"host": [
								"{{host}}"
							],
							"path": [
								"drinks",
								"1"
							]
						}
					},
					"response": []
				},
				{
					"name": "/drinks/1",
					"event": [
						{
							"listen": "test",
							"script": {
								"exec": [
									"pm.test(\"Status code is 401 since no credentials are present\", function () {",
									"    pm.response.to.have.status(401);",
									"});"
								],
								"type": "text/javascript"
							}
						}
					],
					"request": {
						"method": "DELETE",
						"header": [],
						"url": {
							"raw": "{{host}}/drinks/1",
							"host": [
								"{{host}}"
							],
							"path": [
								"drinks",
								"1"
							]
						}
					},
					"response": []
				}
			]
		},
		{
			"name": "barista",
			"item": [
				{
					"name": "/drinks",
					"event": [
						{
							"listen": "test",
							"script": {
								"exec": [
									"pm.test(\"Status code is 200\", function () {",
									"    pm.response.to.have.status(200);",
									"});",
									"",
									"pm.test(\"value contains drinks array\", function () {",
									"    var jsonData = pm.response.json();",
									"    pm.expect(jsonData.drinks).to.be.an('array')",
									"});"
								],
								"type": "text/javascript"
							}
						}
					],
					"request": {
						"method": "GET",
						"header": [],
						"url": {
							"raw": "{{host}}/drinks",
							"host": [
								"{{host}}"
							],
							"path": [
								"drinks"
							]
						}
					},
					"response": []
				},
				{
					"name": "/drinks-detail",
					"event": [
						{
							"listen": "test",
							"script": {
								"exec": [
									"pm.test(\"Status code is 200\", function () {",
									"    pm.response.to.have.status(200);",
									"});"
								],
								"type": "text/javascript"
							}
						}
					],
					"request": {
						"method": "GET",
						"header": [],
						"url": {
							"raw": "{{host}}/drinks-detail",
							"host": [
								"{{host}}"
							],
							"path": [
								"drinks-detail"
							]
						}
					},
					"response": []
				},
				{
					"name": "/drinks",
					"event": [
						{
							"listen": "test",
							"script": {
								"exec": [
									"pm.test(\"Status code is 403 since credentials are valid, but permission is not present\", function () {",
									"    pm.response.to.have.status(403);",
									"});"
								],
								"type": "text/javascript"
							}
						}
					],
					"request": {
						"method": "POST",
						"header": [],
						"url": {
							"raw": "{{host}}/drinks",
							"host": [
								"{{host}}"
							],
							"path": [
								"drinks"
							]
						}
					},
					"response": []
				},
				{
					"name": "/drinks/1",
					"event": [
						{
							"listen": "test",
							"script": {
								"exec": [
									"pm.test(\"Status code is 403 since credentials are valid, but permission is not present\", function () {",
									"    pm.response.to.have.status(403);",
									"});"
								],
								"type": "text/javascript"
							}
						}
					],
					"request": {
						"method": "PATCH",
						"header": [],
						"url": {
							"raw": "{{host}}/drinks/1",
							"host": [
								"{{host}}"
							],
							"path": [
								"drinks",
								"1"
							]
						}
					},
					"response": []
				},
				{
					"name": "/drinks/1",
					"event": [
						{
							"listen": "test",
							"script": {
								"exec": [
									"pm.test(\"Status code is 403 since credentials are valid, but permission is not present\", function () {",
									"    pm.response.to.have.status(403);",
									"});"
								],
								"type": "text/javascript"
							}
						}
					],
					"request": {
						"method": "DELETE",
						"header": [],
						"url": {
							"raw": "{{host}}/drinks/1",
							"host": [
								"{{host}}"
							],
							"path": [
								"drinks",
								"1"
							]
						}
					},
					"response": []
				}
			],
			"auth": {
				"type": "bearer",
				"bearer": [
					{
						"key": "token",
						"value": "eyJhbGciOiJSUzI1NiIsInR5cCI6IkpXVCIsImtpZCI6IlNXemNmRXdUb2Ywc2pfdWZLbzNNcSJ9.eyJ1c2VyLWVtYWlsIjoidWRhY2l0eWJhcmlzdGFAZ21haWwuY29tIiwiaXNzIjoiaHR0cHM6Ly9mc25kLXNvbnktZGV2LnVzLmF1dGgwLmNvbS8iLCJzdWIiOiJhdXRoMHw2NDcwNTllNDkzNDhlNjljNmNjYWM5ZjQiLCJhdWQiOiJkcmlua3MiLCJpYXQiOjE2ODUwODg0NzksImV4cCI6MTY4NTE2MDQ3OSwiYXpwIjoiRlNsV3BMaHBCNWt2ekxtMEgxa00yWm04b3hGMmRaRWsiLCJzY29wZSI6IiIsInBlcm1pc3Npb25zIjpbImdldDpkcmlua3MtZGV0YWlsIl19.Y_OPlzExJJGI_in3warbubPwU4bnr9aSWQ_kycovRzn-vHQrzXiM6V4N9PNDelJCF9PLKDUABDrTwgrSOWVN3optxL7arGlxUlWsFd4GLq8oOvwUlgp0cUKcRiat_o0GFXQlxDYy_iAeYiV-AuabSL6hf5PpU4LjKw8bK0E1gYyKlhKwJ3f-mw7uo7ghWT4CFw59i9DPv8Ur4rKj2hnsB4bLooalIw_321c7ypJdsvP8DL9urnXWpxfJ5FddH_939PcBFFYiIR_BoQUa7SLn5gDaxxJneR7dyj1OWJugsx_JYVAjQxjrX_3g-6g0J3lE_oZQj-Zy9owW81VSw8tuWg",
						"type": "string"
					}
				]
			},
			"event": [
				{
					"listen": "prerequest",
					"script": {
						"type": "text/javascript",
						"exec": [
							""
						]
					}
				},
				{
					"listen": "test",
					"script": {
						"type": "text/javascript",
						"exec": [
							""
						]
					}
				}
			]
		},
		{
			"name": "manager",
			"item": [
				{
					"name": "/drinks",
					"event": [
						{
							"listen": "test",
							"script": {
								"exec": [
									"pm.test(\"Status code is 200\", function () {",
									"    pm.response.to.have.status(200);",
									"});",
									"",
									"pm.test(\"value contains drinks array\", function () {",
									"    var jsonData = pm.response.json();",
									"    pm.expect(jsonData.drinks).to.be.an('array')",
									"});"
								],
								"type": "text/javascript"
							}
						}
					],
					"request": {
						"method": "GET",
						"header": [],
						"url": {
							"raw": "{{host}}/drinks",
							"host": [
								"{{host}}"
							],
							"path": [
								"drinks"
							]
						}
					},
					"response": []
				},
				{
					"name": "/drinks-detail",
					"event": [
						{
							"listen": "test",
							"script": {
								"exec": [
									"pm.test(\"Status code is 200\", function () {",
									"    pm.response.to.have.status(200);",
									"});",
									"",
									"pm.test(\"value contains drinks array\", function () {",
									"    var jsonData = pm.response.json();",
									"    pm.expect(jsonData.drinks).to.be.an('array')",
									"});"
								],
								"type": "text/javascript"
							}
						}
					],
					"request": {
						"method": "GET",
						"header": [],
						"url": {
							"raw": "{{host}}/drinks-detail",
							"host": [
								"{{host}}"
							],
							"path": [
								"drinks-detail"
							]
						}
					},
					"response": []
				},
				{
					"name": "/drinks",
					"event": [
						{
							"listen": "test",
							"script": {
								"exec": [
									"pm.test(\"Status code is 200\", function () {",
									"    pm.response.to.have.status(200);",
									"});"
								],
								"type": "text/javascript"
							}
						}
					],
					"request": {
						"method": "POST",
						"header": [
							{
								"key": "Content-Type",
								"name": "Content-Type",
								"value": "application/json",
								"type": "text"
							}
						],
						"body": {
							"mode": "raw",
							"raw": "{\n    \"title\": \"Water3\",\n    \"recipe\": [{\n        \"name\": \"Water\",\n        \"color\": \"blue\",\n        \"parts\": 1\n    }]\n}"
						},
						"url": {
							"raw": "{{host}}/drinks",
							"host": [
								"{{host}}"
							],
							"path": [
								"drinks"
							]
						}
					},
					"response": []
				},
				{
					"name": "/drinks/1",
					"event": [
						{
							"listen": "test",
							"script": {
								"exec": [
									"pm.test(\"Status code is 200\", function () {",
									"    pm.response.to.have.status(200);",
									"});",
									"",
									"pm.test(\"value contains drinks array\", function () {",
									"    var jsonData = pm.response.json();",
									"    pm.expect(jsonData.drinks).to.be.an('array')",
									"});"
								],
								"type": "text/javascript"
							}
						}
					],
					"request": {
						"method": "PATCH",
						"header": [
							{
								"key": "Content-Type",
								"name": "Content-Type",
								"value": "application/json",
								"type": "text"
							}
						],
						"body": {
							"mode": "raw",
							"raw": "{\n    \"title\": \"Water5\"\n}"
						},
						"url": {
							"raw": "{{host}}/drinks/6",
							"host": [
								"{{host}}"
							],
							"path": [
								"drinks",
								"6"
							]
						}
					},
					"response": []
				},
				{
					"name": "/drinks/1",
					"event": [
						{
							"listen": "test",
							"script": {
								"exec": [
									"pm.test(\"Status code is 200\", function () {",
									"    pm.response.to.have.status(200);",
									"});"
								],
								"type": "text/javascript"
							}
						}
					],
					"request": {
						"method": "DELETE",
						"header": [],
						"url": {
							"raw": "{{host}}/drinks/8",
							"host": [
								"{{host}}"
							],
							"path": [
								"drinks",
								"8"
							]
						}
					},
					"response": []
				}
			],
			"auth": {
				"type": "bearer",
				"bearer": [
					{
						"key": "token",
						"value": "eyJhbGciOiJSUzI1NiIsInR5cCI6IkpXVCIsImtpZCI6IlNXemNmRXdUb2Ywc2pfdWZLbzNNcSJ9.eyJ1c2VyLWVtYWlsIjoidWRhY2l0eW1hbmFnZXJAZ21haWwuY29tIiwiaXNzIjoiaHR0cHM6Ly9mc25kLXNvbnktZGV2LnVzLmF1dGgwLmNvbS8iLCJzdWIiOiJhdXRoMHw2NDcwNTk5OWIwODdmNTc4ZGNjOGFkZDAiLCJhdWQiOiJkcmlua3MiLCJpYXQiOjE2ODUwODg1MjUsImV4cCI6MTY4NTE2MDUyNSwiYXpwIjoiRlNsV3BMaHBCNWt2ekxtMEgxa00yWm04b3hGMmRaRWsiLCJzY29wZSI6IiIsInBlcm1pc3Npb25zIjpbImRlbGV0ZTpkcmlua3MiLCJnZXQ6ZHJpbmtzLWRldGFpbCIsInBhdGNoOmRyaW5rcyIsInBvc3Q6ZHJpbmtzIl19.aUibrltf06LbLk_EwCcW17WmkHvHVP2Luk1a-KUSCyDozDyRrHnM-fFOOg-KFty4LiBK_HTyqewUB9r5zG6xI096oA5j7DJSevHgcGuwMKW9bt2M2dzbMszJD35NS3Nr64M1L0L7ksUWLSilTov3bfCT0i-myx_jKjFZkLsd3sFf5zMn4h7FWoKboX_NNpiMVdHP4yOfjq9sOmeoFVnkmh-lqg6Ki6IOHbzbJtuP7ciKqntBf55QPtSBYiQ59u-TfIUoVK9KmNLI_TgYAcr8xmoeQ22yRyKfXKyusGAo89nsHUNiwayA1afqz7pvJpPRielXEWHFe0WGzzHbMtyR6g",
						"type": "string"
					}
				]
			},
			"event": [
				{
					"listen": "prerequest",
					"script": {
						"type": "text/javascript",
						"exec": [
							""
						]
					}
				},
				{
					"listen": "test",
					"script": {
						"type": "text/javascript",
						"exec": [
							""
						]
					}
				}
			]
		}
	],
	"event": [
		{
			"listen": "prerequest",
			"script": {
				"type": "text/javascript",
				"exec": [
					""
				]
			}
		},
		{
			"listen": "test",
			"script": {
				"type": "text/javascript",
				"exec": [
					""
				]
			}
		}
	],
	"variable": [
		{
			"key": "host",
			"value": "localhost:5000",
			"type": "string"
		}
	]
}